backports/__init__.py
backports/unittest_mock/__init__.py
backports.unittest_mock-1.5.1.dist-info/LICENSE
backports.unittest_mock-1.5.1.dist-info/METADATA
backports.unittest_mock-1.5.1.dist-info/WHEEL
backports.unittest_mock-1.5.1.dist-info/entry_points.txt
backports.unittest_mock-1.5.1.dist-info/top_level.txt
backports.unittest_mock-1.5.1.dist-info/RECORD
